slurmfrag/__init__.py
slurmfrag/__main__.py
slurmfrag/cli.py
slurmfrag/collectors.py
slurmfrag/config.py
slurmfrag/formatters.py
slurmfrag-0.1.0.dist-info/METADATA
slurmfrag-0.1.0.dist-info/WHEEL
slurmfrag-0.1.0.dist-info/entry_points.txt
slurmfrag-0.1.0.dist-info/licenses/LICENSE
slurmfrag-0.1.0.dist-info/RECORD
