Metadata-Version: 2.4
Name: slurmfrag
Version: 0.1.0
Summary: SLURM Fragmentation Analyzer - Visualize and analyze resource fragmentation across SLURM clusters
Project-URL: Homepage, https://github.com/ferreirafabio/slurmfrag
Project-URL: Documentation, https://github.com/ferreirafabio/slurmfrag#readme
Project-URL: Repository, https://github.com/ferreirafabio/slurmfrag
Project-URL: Issues, https://github.com/ferreirafabio/slurmfrag/issues
Author: Fabio Ferreira
License-Expression: Apache-2.0
License-File: LICENSE
Keywords: cluster,fragmentation,gpu,hpc,monitoring,slurm,visualization
Classifier: Development Status :: 4 - Beta
Classifier: Environment :: Console
Classifier: Intended Audience :: Science/Research
Classifier: Intended Audience :: System Administrators
Classifier: License :: OSI Approved :: Apache Software License
Classifier: Operating System :: POSIX :: Linux
Classifier: Programming Language :: Python :: 3
Classifier: Programming Language :: Python :: 3.8
Classifier: Programming Language :: Python :: 3.9
Classifier: Programming Language :: Python :: 3.10
Classifier: Programming Language :: Python :: 3.11
Classifier: Programming Language :: Python :: 3.12
Classifier: Topic :: System :: Clustering
Classifier: Topic :: System :: Monitoring
Classifier: Topic :: System :: Systems Administration
Requires-Python: >=3.8
Requires-Dist: pyyaml>=5.0
Provides-Extra: dev
Requires-Dist: mypy>=1.0; extra == 'dev'
Requires-Dist: pytest-cov>=4.0; extra == 'dev'
Requires-Dist: pytest>=7.0; extra == 'dev'
Requires-Dist: ruff>=0.1.0; extra == 'dev'
